MANIFEST.in
README.md
setup.py
pqsdk/__init__.py
pqsdk/__main__.py
pqsdk/logger.py
pqsdk/main.py
pqsdk/pqconstant.py
pqsdk/version.py
pqsdk.egg-info/PKG-INFO
pqsdk.egg-info/SOURCES.txt
pqsdk.egg-info/dependency_links.txt
pqsdk.egg-info/entry_points.txt
pqsdk.egg-info/requires.txt
pqsdk.egg-info/top_level.txt
pqsdk/api/__init__.py
pqsdk/api/client.py
pqsdk/api/exceptions.py
pqsdk/api/main.py
pqsdk/api/request.py
pqsdk/api/thrift_client.py
pqsdk/api/utils.py
pqsdk/api/compat/__init__.py
pqsdk/api/compat/pickle_compat.py
pqsdk/backtest/__init__.py
pqsdk/backtest/analyzer.py
pqsdk/backtest/context.py
pqsdk/backtest/current_data.py
pqsdk/backtest/instrument.py
pqsdk/backtest/main.py
pqsdk/backtest/order.py
pqsdk/backtest/portfolio.py
pqsdk/backtest/position.py
pqsdk/backtest/run_info.py
pqsdk/enums/__init__.py
pqsdk/enums/orderStatus.py
pqsdk/interface/__init__.py
pqsdk/interface/abstractInstrument.py
pqsdk/interface/abstractOrder.py
pqsdk/interface/abstractPortfolio.py
pqsdk/interface/abstractPosition.py
pqsdk/interface/abstractRunInfo.py
pqsdk/interface/abstractStrategyContext.py
pqsdk/interface/abstractTrader.py
pqsdk/interface/constant.py
pqsdk/utils/__init__.py
pqsdk/utils/dynamic_import.py
pqsdk/utils/file_util.py
pqsdk/utils/import_global_modules.py
pqsdk/utils/threading_utils.py
pqsdk/utils/timer_factory.py
pqsdk/utils/value_type_util.py